aalto_gpu/__init__.py
aalto_gpu/_version.py
aalto_gpu/handlers.py
aalto_gpu/labextension/aalto-gpu-0.1.0.tgz
aalto_gpu-0.1.0.data/data/etc/jupyter/jupyter_notebook_config.d/aalto_gpu.json
aalto_gpu-0.1.0.data/data/share/jupyter/lab/extensions/aalto-gpu-0.1.0.tgz
aalto_gpu-0.1.0.dist-info/LICENSE
aalto_gpu-0.1.0.dist-info/METADATA
aalto_gpu-0.1.0.dist-info/WHEEL
aalto_gpu-0.1.0.dist-info/top_level.txt
aalto_gpu-0.1.0.dist-info/RECORD
