Metadata-Version: 2.1
Name: aalto-gpu
Version: 0.1.0
Summary: An extension designjobs to a kubernetes cluster
Home-page: https://github.com/my_name/myextension
Author: Mikko Murhu
License: BSD-3-Clause
Keywords: Jupyter,JupyterLab
Platform: Linux
Platform: Mac OS X
Platform: Windows
Classifier: License :: OSI Approved :: BSD License
Classifier: Programming Language :: Python
Classifier: Programming Language :: Python :: 3
Classifier: Programming Language :: Python :: 3.5
Classifier: Programming Language :: Python :: 3.6
Classifier: Programming Language :: Python :: 3.7
Classifier: Programming Language :: Python :: 3.8
Classifier: Framework :: Jupyter
Requires-Python: >=3.5
Requires-Dist: jupyterlab (~=2.0)
